play_cassandra/__init__.py
play_cassandra/providers.py
play_cassandra-0.0.4.dist-info/LICENSE
play_cassandra-0.0.4.dist-info/METADATA
play_cassandra-0.0.4.dist-info/WHEEL
play_cassandra-0.0.4.dist-info/entry_points.txt
play_cassandra-0.0.4.dist-info/top_level.txt
play_cassandra-0.0.4.dist-info/RECORD
